MANIFEST.in
README.md
setup.py
CassandraJsonMapper/CassandraJsonMapper.py
CassandraJsonMapper/__init__.py
CassandraJsonMapper.egg-info/PKG-INFO
CassandraJsonMapper.egg-info/SOURCES.txt
CassandraJsonMapper.egg-info/dependency_links.txt
CassandraJsonMapper.egg-info/requires.txt
CassandraJsonMapper.egg-info/top_level.txt