Metadata-Version: 1.0
Name: CassandraJsonMapper
Version: 1.2.1
Summary: Simple JSON to Cassandra Python client.
Home-page: http://www.github.com/joaquincasares/CassandraJsonMapper
Author: Joaquin Casares
Author-email: joaquin.casares AT gmail.com
License: UNKNOWN
Keywords: apache cassandra json mapper simple client
Platform: UNKNOWN
